<?xml version="1.0" encoding="utf-8" ?>
<manifest>
  <control namespace="SampleNamespace" constructor="PortalWebAPIControl" version="0.0.1" display-name-key="PortalWebAPIControl_Display_Key" description-key="PortalWebAPIControl_Desc_Display_Key" control-type="standard">    
    <property name="stringProperty" display-name-key="stringProperty_Display_Key" description-key="stringProperty_Desc_Key" of-type="SingleLine.Text" usage="bound" required="true" />   
    <resources>
      <code path="index.ts" order="1"/>
      <css path="css/PortalWebAPIControl.css" order="2" />
      <resx path="strings/PortalWebAPIControl.1033.resx" version="1.0.0" />
    </resources>
    <feature-usage>     
      <uses-feature name="WebAPI" required="true" />
    </feature-usage>
  </control>
</manifest>
